README.md
setup.cfg
setup.py
alice_and_bob/__init__.py
alice_and_bob/key_share.py
alice_and_bob/primes.py
alice_and_bob.egg-info/PKG-INFO
alice_and_bob.egg-info/SOURCES.txt
alice_and_bob.egg-info/dependency_links.txt
alice_and_bob.egg-info/entry_points.txt
alice_and_bob.egg-info/requires.txt
alice_and_bob.egg-info/top_level.txt
test/test_key_share.py
test/test_primes.py